FragmentAPI/__init__.py
FragmentAPI/async_client.py
FragmentAPI/core.py
FragmentAPI/exceptions.py
FragmentAPI/models.py
FragmentAPI/sync_client.py
FragmentAPI/utils.py
FragmentAPI/wallet.py
fragment_api_py-3.2.0.dist-info/METADATA
fragment_api_py-3.2.0.dist-info/WHEEL
fragment_api_py-3.2.0.dist-info/top_level.txt
fragment_api_py-3.2.0.dist-info/RECORD
